myshare_mcp/__init__.py
myshare_mcp/server.py
myshare_mcp/myshare/__init__.py
myshare_mcp/myshare/data.py
myshare_mcp/myshare/eastmoney.py
myshare_mcp/myshare/utils.py
myshare_mcp/myshare/xq.py
myshare_mcp-0.1.10.dist-info/METADATA
myshare_mcp-0.1.10.dist-info/WHEEL
myshare_mcp-0.1.10.dist-info/entry_points.txt
myshare_mcp-0.1.10.dist-info/RECORD
