Metadata-Version: 2.4
Name: myshare_mcp
Version: 0.1.10
Summary: A Model Context Protocol server for Financial Analysis
Author-email: Roger Ye <shugaoye@yahoo.com>
Keywords: agent,broker,finance,investment,mcp,model context protocol,robinhood,trading,wallstreetbets
Classifier: Intended Audience :: End Users/Desktop
Classifier: Intended Audience :: Financial and Insurance Industry
Classifier: License :: OSI Approved :: MIT License
Classifier: Programming Language :: Python :: 3.12
Classifier: Topic :: Office/Business :: Financial
Requires-Python: >=3.12
Requires-Dist: akshare>=1.16.81
Requires-Dist: fastapi>=0.115.12
Requires-Dist: ipykernel>=6.29.5
Requires-Dist: ipywidgets>=8.1.6
Requires-Dist: mcp[cli]>=1.6.0
Requires-Dist: pandas>=2.2.3
Requires-Dist: pytest>=8.3.5
Requires-Dist: sqlalchemy>=2.0.40
Requires-Dist: sqlite-web>=0.6.4
Requires-Dist: uvicorn>=0.34.2
